awscli_saml_sso/__init__.py
awscli_saml_sso/animated.gif
awscli_saml_sso/browser.py
awscli_saml_sso/config_parser.py
awscli_saml_sso/driver.py
awscli_saml_sso/first_time.html
awscli_saml_sso/logger.cfg
awscli_saml_sso/main.py
awscli_saml_sso-0.3.2.dist-info/AUTHORS.rst
awscli_saml_sso-0.3.2.dist-info/LICENSE
awscli_saml_sso-0.3.2.dist-info/METADATA
awscli_saml_sso-0.3.2.dist-info/WHEEL
awscli_saml_sso-0.3.2.dist-info/entry_points.txt
awscli_saml_sso-0.3.2.dist-info/top_level.txt
awscli_saml_sso-0.3.2.dist-info/RECORD
