Metadata-Version: 2.1
Name: awscli-saml-sso
Version: 0.3.2
Summary: awscli_saml_sso is a command line tool that aims to get temporary credentials from SAML identity 
Home-page: https://github.com/octo-technology/awscli-saml-sso
Author: Benjamin Brabant
Author-email: benjamin.brabant@octo.com
License: GNU General Public License v3
Keywords: awscli,saml,sso
Classifier: Intended Audience :: Developers
Classifier: License :: OSI Approved :: GNU General Public License v3 (GPLv3)
Classifier: Natural Language :: English
Classifier: Programming Language :: Python :: 3
Classifier: Programming Language :: Python :: 3.8
Classifier: Programming Language :: Python :: 3.9
Classifier: Programming Language :: Python :: 3.10
Classifier: Programming Language :: Python :: 3.11
Requires-Python: >=3.8,<3.12
License-File: LICENSE
License-File: AUTHORS.rst
Requires-Dist: boto3==1.16.26
Requires-Dist: click==7.1.2
Requires-Dist: selenium==4.21.0
Requires-Dist: selenium-wire==5.1.0
Requires-Dist: webdriver-manager==4.0.1
Requires-Dist: keyring==25.4.1
Requires-Dist: blinker==1.7.0
Requires-Dist: pyopenssl==22.0.0
Requires-Dist: cryptography==38.0.4
Requires-Dist: h2==4.1.0
Requires-Dist: setuptools==65.5.0
